Workbook

Sheet Legend
A1: Category-wise steps for confirmed programs
A2: Legend for time-limits within which things need to be done:
A4: Symbol | B4: Meaning | C4: Date | D4: Notes | E4: Milestone
A5: R | B5: stands for date of receiving RFP | C5: 46113 | D5: Input actual date of receiving RFP | E5: Working on RFP
A6: R+ | B6: stands for no. of days after receiving RFP
A7: S | B7: stands for proposal submission date | C7: =$C$5+15 -> 46128 | D7: Input actual deadline of submitting proposal or Actual date of submitting proposal | E7: Working on RFP
A8: S-/+ | B8: stands for no. of days before/after proposal submission date
A9: W | B9: stands for date when client approves our proposal | D9: Input actual date when program is won | E9: Planning
A10: C | B10: stands for date of confirmation (for repeat clients, this can be when they tell us group size) | C10: 46130 | D10: Input actual date of program confirmation | E10: Planning
A11: C+ | B11: stands for no. of days after confirmation/go-ahead received from client
A12: P | B12: stands for program dates | C12: 46147 | D12: Input actual program start date | E12: Delivery
A13: PE | B13: stands for program end date | C13: 46157 | D13: Input actual program end date | E13: Delivery
A14: P- | B14: stands for no. of days before program start
A15: P+ | B15: stands for no. of days after the program ends

Sheet Faculty Led Programs
A1: Operations Process (Proposal to Delivery)
A3: Action Items while sending proposals
A4: Name | B4: Timeframe (Date) | C4: Timeframe (Date) | D4: Milestone | E4: Notes | F4: Process # | G4: Timeline - Start | H4: Timeline - End
A5: Ensure sales hand-off template is filled; clarify doubts, if any before working on the proposal | B5: R+1 | C5: =Legend!$C$5+1 -> 46114 | D5: Working on RFP | E5: Hand-off to ops team
A6: Detail out the requirements and send it to DMCs/Vendors | B6: R+2 | C6: =Legend!$C$5+2 -> 46115 | D6: Working on RFP | E6: Using draft itinerary template
A7: Create a costing sheet with quotes from DMCs/hotels | B7: R+7 | C7: =Legend!$C$5+7 -> 46120 | D7: Working on RFP
A8: Complete and review the costing sheet and proposal | B8: R+9 | C8: =Legend!$C$5+9 -> 46122 | D8: Working on RFP | E8: Use formats like hotel sheet to finalize hotel options
A9: Submit proposal to client | B9: S | C9: =Legend!$C$7 -> 46128 | D9: Working on RFP | E9: Sales team submits the proposal
A10: Block all proposed hotels and guides | B10: S | C10: =Legend!$C$7 -> 46128 | D10: Working on RFP | E10: ensure payments & cancellation are on agreeable terms
A11: Followup with client/sales on the proposal status to release or keep the blocks | B11: S+10 | C11: =Legend!$C$7+10 -> 46138 | D11: Working on RFP | E11: Proposal confirmation timeline could vary
A13: Action Items after proposal is won
A14: Name | B14: Timeframe (Date) | C14: Timeframe (Date) | D14: Milestone | E14: Notes | F14: Process # | G14: Timeline - Start | H14: Timeline - End
A15: Sign contracts with hotels and DMCs | B15: W+1 | C15: =Legend!$C$9+1 -> 1 | D15: Planning | E15: timeframe could vary
A16: Followup with client/sales on program confirmation date | B16: P-76 | C16: =Legend!$C$12-76 -> 46071 | D16: Planning | E16: timeframe could vary
A18: Action Items after program confirmation
A19: Name | B19: Timeframe (Date) | C19: Timeframe (Date) | D19: Milestone | E19: Notes | F19: Process # | G19: Timeline - Start | H19: Timeline - End
A20: Send deposit invoice to university | B20: P-76 | C20: =Legend!$C$12-76 -> 46071 | D20: Planning | E20: Check proposal terms and conditions
A21: Create mastersheet | B21: C+3 | C21: =Legend!$C$10+3 -> 46133 | D21: Planning | E21: Use template and fill information on an on-going basis
A22: Set up Monday.com/google sheet for collaboration with all university stakeholders | B22: C+3 | C22: =Legend!$C$10+3 -> 46133 | D22: Planning | E22: ENHANCED: Real-time tracking
A23: Share participant data template to collect information (including scanned passport copies) | B23: C+7 | C23: =Legend!$C$10+7 -> 46137 | D23: Planning | E23: Use participant data template #to client
A24: Send balance invoice to university | B24: P-32 | C24: =Legend!$C$12-32 -> 46115 | D24: Planning
A25: Get confirmation on final service requirements from university | B25: P-32 | C25: =Legend!$C$12-32 -> 46115 | D25: Planning | E25: Confirm final group size, hotel blocks, transport, guides, meals, academic content and cultural immersions
A26: Send final program services agreement | B26: P-22 | C26: =Legend!$C$12-22 -> 46125 | D26: Planning
A27: Prepare for in-person/online program orientation and safety briefing | B27: P-22 | C27: =Legend!$C$12-22 -> 46125 | D27: Planning | E27: Refer to India orientation PPT
A28: Create and share pre-departure guide | B28: P-22 | C28: =Legend!$C$12-22 -> 46125 | D28: Planning | E28: Refer to standard pre dep template
A29: Create checklist for delivery | B29: P-10 | C29: =Legend!$C$12-10 -> 46137 | D29: Delivery | E29: Refer to mastersheet for template
A30: Plan and prepare first aid kits and other relevant material specific to programs | B30: P-5 | C30: =Legend!$C$12-5 -> 46142 | D30: Delivery
A31: Print checklists and relevant documents | B31: P-5 | C31: =Legend!$C$12-5 -> 46142 | D31: Delivery
A32: Send post program invoice to the university | B32: PE+10 | C32: =Legend!$C$13+10 -> 46167 | D32: Delivery | E32: Enter Program end date + 7 days
A33: Send thank you notes to partner organizations / companies | B33: PE+5 | C33: =Legend!$C$13+5 -> 46162 | D33: Delivery | E33: Send thank you notes on the same day of the visit (could vary based on the work load)
A36: Pre-departure planning
A37: Name | B37: Timeframe (Date) | C37: Timeframe (Date) | D37: Milestone | E37: Notes | F37: Process # | G37: Timeline - Start | H37: Timeline - End
A38: Mandatory vendor service specification documentation | B38: P-22 | C38: =Legend!$C$12-22 -> 46125 | D38: Planning | E38: NEW: All limitations documented
A39: Complete program orientation for guides and local partners | B39: P-22 | C39: =Legend!$C$12-22 -> 46125 | D39: Planning | E39: Brief them about Authentica standards
A42: Triple Verification Protocol
A43: Name | B43: Timeframe (Date) | C43: Timeframe (Date) | D43: Milestone | E43: Notes | F43: Process # | G43: Timeline - Start | H43: Timeline - End
A44: Verify pre-program delivery checklist | B44: P-5 | C44: =Legend!$C$12-5 -> 46142 | D44: Planning | E44: Refer template
A46: Hotels
A47: Name | B47: Timeframe (Date) | C47: Timeframe (Date) | D47: Milestone | E47: Notes | F47: Process # | G47: Timeline - Start | H47: Timeline - End
A48: Block and sign contracts with chosen hotels and procure invoices with payment details | B48: W+1 | C48: =Legend!$C$9+1 -> 1 | D48: Planning | E48: As per updated numbers received from the university
A49: Release block for other hotels across locations | B49: W+1 | C49: =Legend!$C$9+1 -> 1 | D49: Planning
A50: Reconfirm number of rooms after we receive confirmed group size | B50: C+1 | C50: =Legend!$C$10+1 -> 46131 | D50: Planning
A51: Send advance to chosen hotels: CCA / bank transfer / outward remittance | B51: P-66 | C51: =Legend!$C$12-66 -> 46081 | D51: Planning | E51: could vary
A52: Collect rooming list from client and send it to hotels | B52: P-15 | C52: =Legend!$C$12-15 -> 46132 | D52: Delivery
A54: Flight/Train bookings
A55: Name | B55: Timeframe (Date) | C55: Timeframe (Date) | D55: Milestone | E55: Notes | F55: Process # | G55: Timeline - Start | H55: Timeline - End
A56: Confirm preferred flight/train option with client | B56: P-44 | C56: =Legend!$C$12-44 -> 46103 | D56: Planning | E56: could vary
A57: Collect participant information / passport scans | B57: P-44 | C57: =Legend!$C$12-44 -> 46103 | D57: Planning | E57: could vary
A58: Book tickets (either with vendor or directly online) and share tickets with university | B58: P-39 | C58: =Legend!$C$12-39 -> 46108 | D58: Planning | E58: could vary
A60: Guides
A61: Name | B61: Timeframe (Date) | C61: Timeframe (Date) | D61: Milestone | E61: Notes | F61: Process # | G61: Timeline - Start | H61: Timeline - End
A62: Book dates of preferred guides (Directly or with DMC) | B62: W+5 | C62: =Legend!$C$9+5 -> 5 | D62: Planning
A63: Send draft itinerary to guides/DMC along with the academic objective briefing | B63: P-22 | C63: =Legend!$C$12-22 -> 46125 | D63: Planning
A64: Send final itinerary / checklist and PAX info to guides | B64: P-10 | C64: =Legend!$C$12-10 -> 46137 | D64: Delivery | E64: could vary
A66: Meeting Rooms
A67: Name | B67: Timeframe (Date) | C67: Timeframe (Date) | D67: Milestone | E67: Notes | F67: Process # | G67: Timeline - Start | H67: Timeline - End
A68: Confirm exact requirement from client (preferred venue location, purpose of meeting, group size, AV requirement, F&B etc.) | B68: P-44 | C68: =Legend!$C$12-44 -> 46103 | D68: Planning
A69: Identify, block and finalize venue | B69: P-39 | C69: =Legend!$C$12-39 -> 46108 | D69: Planning
A70: Pay advance, if needed | B70: P-22 | C70: =Legend!$C$12-22 -> 46125 | D70: Planning | E70: could vary
A71: Re-confirm exact requirements from university and share it with vendors | B71: P-10 | C71: =Legend!$C$12-10 -> 46137 | D71: Delivery
A73: Transport
A74: Name | B74: Timeframe (Date) | C74: Timeframe (Date) | D74: Milestone | E74: Notes | F74: Process # | G74: Timeline - Start | H74: Timeline - End
A75: Confirm requirement for each destination / specific visits or requirements (e.g. seatbelts, wheelchair acess etc.) and share with vendors/DMC | B75: P-44 | C75: =Legend!$C$12-44 -> 46103 | D75: Planning
A76: Send transport/DMC itinerary to check about routes, timings or any specific requirements/issues | B76: P-22 | C76: =Legend!$C$12-22 -> 46125 | D76: Planning
A77: Share arrival and departure schedule to university and share it with vendors/DMC | B77: P-15 | C77: =Legend!$C$12-15 -> 46132 | D77: Planning | E77: As per the mastersheet template
A78: Send final itinerary and placard | B78: P-10 | C78: =Legend!$C$12-10 -> 46137 | D78: Planning | E78: Asian DMCs require this earlier
A80: Meals
A81: Name | B81: Timeframe (Date) | C81: Timeframe (Date) | D81: Milestone | E81: Notes | F81: Process # | G81: Timeline - Start | H81: Timeline - End
A82: Confirm meal requirements to be included | B82: P-44 | C82: =Legend!$C$12-44 -> 46103 | D82: Planning
A83: Research appropriate options in each destination (if not done already) | B83: P-42 | C83: =Legend!$C$12-42 -> 46105 | D83: Planning | E83: sometimes we have specific seating requirement
A84: Contact shortlisted venues to get availability, rates and menu details | B84: P-40 | C84: =Legend!$C$12-40 -> 46107 | D84: Planning
A85: Finalilze and block chosen venues | B85: P-39 | C85: =Legend!$C$12-39 -> 46108 | D85: Planning | E85: sometimes client approval is needed
A86: Pay advance, if needed | B86: P-22 | C86: =Legend!$C$12-22 -> 46125 | D86: Planning
A87: Send dietary restrictions | B87: P-22 | C87: =Legend!$C$12-22 -> 46125 | D87: Planning
A88: Finalize menu with dietary restrictions | B88: P-15 | C88: =Legend!$C$12-15 -> 46132 | D88: Planning | E88: sometimes client approval is needed
A89: Reconfirm seating and menu | B89: P-1 | C89: =Legend!$C$12-1 -> 46146 | D89: Delivery
A91: Immersions
A92: Name | B92: Timeframe (Date) | C92: Timeframe (Date) | D92: Milestone | E92: Notes | F92: Process # | G92: Timeline - Start | H92: Timeline - End
A93: Finalilze and block chosen options with any specific instruction (e.g. specific guides, atomic bomb survivor etc.) | B93: P-44 | C93: =Legend!$C$12-44 -> 46103 | D93: Planning | E93: sometimes client approval is needed
A94: Pay advance, if needed | B94: P-22 | C94: =Legend!$C$12-22 -> 46125 | D94: Planning
A96: Org Visits
A97: Name | B97: Timeframe (Date) | C97: Timeframe (Date) | D97: Milestone | E97: Notes | F97: Process # | G97: Timeline - Start | H97: Timeline - End
A98: Brief PDs/Content partners regarding program theme and requirements | B98: C+1 | C98: =Legend!$C$10+1 -> 46131 | D98: Planning
A99: Collect relevant info to be shared (e.g. bio book) from client | B99: P-22 | C99: =Legend!$C$12-22 -> 46125 | D99: Planning
A100: Finalize visits in discussion with the client and PDs | B100: P-22 | C100: =Legend!$C$12-22 -> 46125 | D100: Planning
A101: Get logistical contacts from PDs at for each visit | B101: P-22 | C101: =Legend!$C$12-22 -> 46125 | D101: Planning
A102: Co-ordinate with organizations about the visit (timings, address, meals, security protocols like passports, roster sheet, license plate) | B102: P-10 | C102: =Legend!$C$12-10 -> 46137 | D102: Planning
A103: Plan and procure gifts for organization visits | B103: P-22 | C103: =Legend!$C$12-22 -> 46125 | D103: Planning
A106: Post Program Action items
A107: Name | B107: Timeframe (Date) | C107: Timeframe (Date) | D107: Milestone | E107: Notes | F107: Process # | G107: Timeline - Start | H107: Timeline - End
A108: Send post program invoice to the university | B108: PE+10 | C108: =Legend!$C$13+10 -> 46167 | D108: Delivery | E108: Enter Program end date + 7 days
A109: Send thank you notes to partner organizations / companies | B109: PE+5 | C109: =Legend!$C$13+5 -> 46162 | D109: Delivery | E109: Send thank you notes on the same day of the visit (could vary based on the work load)
A110: Settle balance payments of all vendors | B110: PE+10 | C110: =Legend!$C$13+10 -> 46167 | D110: Delivery
A111: Submit expense report to HQ | B111: PE+10 | C111: =Legend!$C$13+10 -> 46167 | D111: Delivery
A112: Upload media to zoho drive | B112: PE+10 | C112: =Legend!$C$13+10 -> 46167 | D112: Delivery
A113: Service failure compensation processing | B113: PE+15 | C113: =Legend!$C$13+15 -> 46172 | D113: Delivery | E113: NEW: Proactive client relations
A114: Local partner performance evaluation | B114: PE+15 | C114: =Legend!$C$13+15 -> 46172 | D114: Delivery | E114: NEW: Continuous improvement
A115: Process improvement documentation | B115: PE+15 | C115: =Legend!$C$13+15 -> 46172 | D115: Delivery | E115: Use learnings template in Mastersheet
A116: Debrief with all stakeholders | B116: PE+22 | C116: =Legend!$C$13+22 -> 46179 | D116: Delivery | E116: NEW: Rapid issue identification
A119: Document Version History
...
