Workbook

Sheet Legend
A1: Category-wise steps for confirmed programs
A2: Legend for time-limits within which things need to be done:
A4: Symbol | B4: Meaning | C4: Date | D4: Notes | E4: Milestone
A5: R | B5: stands for date of receiving RFP | C5: 46082 | D5: Input actual date of receiving RFP | E5: Working on RFP
A6: R+ | B6: stands for no. of days after receiving RFP
A7: S | B7: stands for proposal submission date | C7: =$C$5+14 -> 46096 | D7: Input actual deadline of submitting proposal or Actual date of submitting proposal | E7: Working on RFP
A8: S-/+ | B8: stands for no. of days before/after proposal submission date
A9: C | B9: stands for date of confirmation (for repeat clients, this can be when they tell us group size) | C9: 46101 | D9: Input actual date of program confirmation | E9: Planning
A10: C+ | B10: stands for no. of days after confirmation/go-ahead received from client
A11: P | B11: stands for program dates | C11: 46130 | D11: Input actual program start date | E11: Delivery
A12: PE | B12: stands for program end date | C12: 46234 | D12: Input actual program end date | E12: Delivery
A13: P- | B13: stands for no. of days before program start
A14: P+ | B14: stands for no. of days after the program ends

Sheet Operations Process
A1: Operations Process (Proposal to Delivery)
A3: Action Items while sending proposals
A4: Name | B4: Timeframe (Date) | C4: Timeframe (Date) | D4: Milestone | E4: Notes | F4: Process # | G4: Timeline - Start | H4: Timeline - End
A5: Ensure sales hand-off template is filled; clarify doubts, if any before working on the proposal | B5: R | C5: =Legend!$C$5 -> 46082 | D5: Working on RFP
A6: Use itinerary elements template to detail out the requirements | B6: R+1 | C6: =Legend!$C$5+1 -> 46083 | D6: Working on RFP
A7: Use vendor template to reach out to DMCs etc. | B7: R+1 | C7: =Legend!$C$5+1 -> 46083 | D7: Working on RFP
A8: Decide FOC etc. terms with hotels | B8: R+7 | C8: =Legend!$C$5+7 -> 46089 | D8: Working on RFP
A9: Use hotel options, dining options etc. templates to save all information | B9: R+7 | C9: =Legend!$C$5+7 -> 46089 | D9: Working on RFP
A10: Document all vendor service limitations and requirements | B10: R+7 | C10: =Legend!$C$5+7 -> 46089 | D10: Working on RFP | E10: NEW: Capture luggage transfer limits, group size restrictions, etc.
A11: Verify accommodation standards meet university requirements (private bathrooms, accessibility) | B11: R+7 | C11: =Legend!$C$5+7 -> 46089 | D11: Working on RFP | E11: NEW: Based on Cats Hostel Madrid issue
A12: Complete work on costing sheet and proposal formats | B12: R+7 | C12: =Legend!$C$5+7 -> 46089 | D12: Working on RFP
A13: Include detailed transportation requirements template (airport transfers, public transit specifications) | B13: S-1 | C13: =Legend!$C$7-1 -> 46095 | D13: Working on RFP | E13: NEW: Based on Barcelona transit confusion
A14: Do a thorough proof-reading and cross-checking (with help from another team member) | B14: S-1 | C14: =Legend!$C$7-1 -> 46095 | D14: Working on RFP
A15: Ensure block on all hotels and important resources while sending proposals | B15: S | C15: =Legend!$C$7 -> 46096 | D15: Working on RFP | E15: ensure payments & cancellation are on agreeable terms
A16: Followup with client on the proposal status | B16: S+15 | C16: =Legend!$C$7+15 -> 46111 | D16: Working on RFP | E16: could vary
A19: Action Items after program confirmation
A20: Name | B20: Timeframe (Date) | C20: Timeframe (Date) | D20: Milestone | E20: Notes | F20: Process # | G20: Timeline - Start | H20: Timeline - End
A21: Send advance invoice | B21: P-90 | C21: =Legend!$C$11-90 -> 46040 | D21: Planning
A22: Create mastersheet and fill up all tabs with information till date | B22: C+1 | C22: =Legend!$C$9+1 -> 46102 | D22: Planning
A23: Implement triple verification system for all bookings | B23: C+3 | C23: =Legend!$C$9+3 -> 46104 | D23: Planning | E23: ENHANCED: Real-time tracking
A24: Set up Monday.com collaboration board with university stakeholders | B24: C+3 | C24: =Legend!$C$9+3 -> 46104 | D24: Planning | E24: ENHANCED: Real-time tracking
A25: Create and share googlesheets to collect information from client | B25: C+7 | C25: =Legend!$C$9+7 -> 46108 | D25: Planning
A26: Prepare orientation ppt / other such information (e.g. language workshop, empathy workshop etc.) | B26: P-30 | C26: =Legend!$C$11-30 -> 46100 | D26: Planning
A27: Send balance invoice | B27: P-30 | C27: =Legend!$C$11-30 -> 46100 | D27: Planning
A28: Update emergency action plan for the program | B28: P-30 | C28: =Legend!$C$11-30 -> 46100 | D28: Planning
A29: Establish clear protocols for mid-program change requests | B29: P-30 | C29: =Legend!$C$11-30 -> 46100 | D29: Planning | E29: NEW: Based on OSU budget change requests
A30: Create and share pre-dep information / dossier | B30: P-30 | C30: =Legend!$C$11-30 -> 46100 | D30: Planning
A31: Include comprehensive service limitations in student materials | B31: P-30 | C31: =Legend!$C$11-30 -> 46100 | D31: Planning | E31: ENHANCED: Luggage specs, transit rules
A32: Create checklist for delivery | B32: P-15 | C32: =Legend!$C$11-15 -> 46115 | D32: Delivery
A33: Continue updating mastersheet on regular basis | B33: P-7 | C33: =Legend!$C$11-7 -> 46123 | D33: Delivery
A34: Create documentation and communication plan | B34: P-7 | C34: =Legend!$C$11-7 -> 46123 | D34: Delivery
A35: Plan and prepare first aid kits and other relevant material specific to programs | B35: P-7 | C35: =Legend!$C$11-7 -> 46123 | D35: Delivery
A36: Print checklists and relevant documents | B36: P-15 | C36: =Legend!$C$11-1 -> 46129 | D36: Delivery
A37: Note any additional expenses beyond what we have invoiced for | B37: P | C37: =Legend!$C$11-7 -> 46123 | D37: Delivery | E37: sometimes things are added even before program
A38: Send payment links to individuals for single supp/extra nights/activities (e.g. baseball match) etc. | B38: P | C38: =Legend!$C$11-7 -> 46123 | D38: Delivery | E38: time-frame could vary
A39: Send invoice to client for additional expenses | B39: P+7 | C39: =Legend!$C$12 -> 46234 | D39: Delivery | E39: Enter Program end date + 7 days
A40: Send thank you notes to partner organizations / companies | B40: P+7 | C40: =Legend!$C$12 -> 46234 | D40: Delivery | E40: Send thank you notes on the same day of the visit (could vary based on the work load)
A43: Pre-departure planning
A44: Name | B44: Timeframe (Date) | C44: Timeframe (Date) | D44: Milestone | E44: Notes | F44: Process # | G44: Timeline - Start | H44: Timeline - End
A45: Mandatory vendor service specification documentation | B45: C+45 | C45: =Legend!$C$5+45 -> 46127 | D45: Working on RFP | E45: NEW: All limitations documented
A46: Local partner certification training completion | B46: C+45 | C46: =Legend!$C$5+45 -> 46127 | D46: Working on RFP | E46: NEW: University program standards
A47: Accessibility assessment for all activities and routes | B47: C+40 | C47: =Legend!$C$5+40 -> 46122 | D47: Working on RFP | E47: NEW: San Sebastian route equity issue
A48: Weather contingency planning for all group activities | B48: C+35 | C48: =Legend!$C$5+35 -> 46117 | D48: Working on RFP | E48: NEW: San Sebastian dinner issue
A49: Restaurant proximity verification (max 10min walk from accommodations) | B49: C+35 | C49: =Legend!$C$5+35 -> 46117 | D49: Working on RFP | E49: NEW: Spain group dinner locations
A52: Triple Verification Protocol
A53: Name | B53: Timeframe (Date) | C53: Timeframe (Date) | D53: Milestone | E53: Notes | F53: Process # | G53: Timeline - Start | H53: Timeline - End
A54: First verification: All bookings confirmed with vendors | B54: P-15 | C54: =Legend!$C$11-15 -> 46115 | D54: Planning | E54: NEW: Screenshot confirmations required
A55: Second verification: Room counts, amenity specifications | B55: P-7 | C55: =Legend!$C$11-7 -> 46123 | D55: Planning | E55: NEW: Private bathroom verification
A56: Third verification: Final headcount updates to all vendors | B56: P-2 | C56: =Legend!$C$11-2 -> 46128 | D56: Delivery | E56: NEW: Prevent overbooking issues
A57: Pre-program vendor briefing calls (hotels, transport, guides) | B57: P-2 | C57: =Legend!$C$11-2 -> 46128 | D57: Delivery | E57: NEW: 72-hour advance coordination
A58: Transit pass delivery confirmation (24hrs before first use) | B58: P-2 | C58: =Legend!$C$11-2 -> 46128 | D58: Delivery | E58: NEW: San Sebastian dinner issue prevention
A59: Driver briefing with printed itineraries in local language | B59: P-2 | C59: =Legend!$C$11-2 -> 46128 | D59: Delivery | E59: NEW: Spain bus coordination issue
A62: Hotels
A63: Name | B63: Timeframe (Date) | C63: Timeframe (Date) | D63: Milestone | E63: Notes | F63: Process # | G63: Timeline - Start | H63: Timeline - End
A64: Confirm room requirement and configurations from client | B64: C+7 | C64: =Legend!$C$9+7 -> 46108 | D64: Planning | E64: sometimes this gets modified later
A65: Re-confirm block for chosen hotels across locations (refer notes) | B65: C+1 | C65: =Legend!$C$9+1 -> 46102 | D65: Planning | E65: this could involve contracting
A66: Release block for other hotels across locations | B66: C+7 | C66: =Legend!$C$9+7 -> 46108 | D66: Planning
A67: Sign contracts with chosen hotels and procure invoices with payment details | B67: C+30 | C67: =Legend!$C$9+30 -> 46131 | D67: Planning | E67: hotel's contract format
A68: Send advance to chosen hotels: CCA / bank transfer / outward remittance | B68: C+30 | C68: =Legend!$C$9+30 -> 46131 | D68: Delivery | E68: could vary
A69: Collect rooming list from client | B69: P-15 | C69: =Legend!$C$11-15 -> 46115 | D69: Delivery
A70: Final enrollment number update to all vendors | B70: P-15 | C70: =Legend!$C$11-15 -> 46115 | D70: Delivery | E70: NEW: Tsukuba hotel room issue prevention
A71: Send rooming list to hotels | B71: P-7 | C71: =Legend!$C$11-7 -> 46123 | D71: Delivery
A72: Ensure rooms are allocated as per requirement | B72: P-1 | C72: =Legend!$C$11-1 -> 46129 | D72: Delivery
A73: Sort out any issues with the rooms in discussion with the duty manager | B73: P | C73: =Legend!$C$11 -> 46130 | D73: Delivery
A74: Settle balance payments within | B74: P+7 | C74: =Legend!$C$12+7 -> 46241 | D74: Delivery | E74: Program end date
A77: Flight/Train bookings
A78: Name | B78: Timeframe (Date) | C78: Timeframe (Date) | D78: Milestone | E78: Notes | F78: Process # | G78: Timeline - Start | H78: Timeline - End
A79: Confirm preferred flight/train option with client | B79: C+1 | C79: =Legend!$C$9+1 -> 46102 | D79: Delivery | E79: could vary
A80: Decide whether you would approach some vendor or book online directly | B80: C+1 | C80: =Legend!$C$9+1 -> 46102 | D80: Delivery | E80: could vary
A81: Collect participant information / passport scans | B81: C+7 | C81: =Legend!$C$9+7 -> 46108 | D81: Delivery | E81: could vary
A82: Book flights/trains | B82: C+15 | C82: =Legend!$C$9+15 -> 46116 | D82: Delivery | E82: could vary
A83: Share tickets with client | B83: P-30 | C83: =Legend!$C$11-30 -> 46100 | D83: Delivery
A86: Guides
A87: Name | B87: Timeframe (Date) | C87: Timeframe (Date) | D87: Milestone | E87: Notes | F87: Process # | G87: Timeline - Start | H87: Timeline - End
A88: Re-confirm block for chosen guides | B88: C+1 | C88: =Legend!$C$9+1 -> 46102 | D88: Planning
A89: Send draft itinerary to guides | B89: P-30 | C89: =Legend!$C$11-30 -> 46100 | D89: Planning
A90: Academic objectives briefing with all guides and vendors | B90: P-15 | C90: =Legend!$C$11-15 -> 46115 | D90: Delivery | E90: NEW: Spain tour guide role clarification
A91: Send final itinerary / checklist and PAX info to guides | B91: P-7 | C91: =Legend!$C$11-7 -> 46123 | D91: Delivery | E91: could vary
A92: Send advance for entrance fees etc. | B92: P-1 | C92: =Legend!$C$11-1 -> 46129 | D92: Delivery
A93: Be in touch on a daily basis to ensure things are going as per plan / discuss necessary modifications | B93: P | C93: =Legend!$C$11 -> 46130 | D93: Delivery
A94: Settle accounts | B94: P+7 | C94: =Legend!$C$12+7 -> 46241 | D94: Delivery
A97: Meeting Rooms
A98: Name | B98: Timeframe (Date) | C98: Timeframe (Date) | D98: Milestone | E98: Notes | F98: Process # | G98: Timeline - Start | H98: Timeline - End
A99: Re-confirm exact requirement from client (preferred venue location, purpose of meeting, group size, AV requirement, F&B etc.) | B99: C+1 | C99: =Legend!$C$9+1 -> 46102 | D99: Working on RFP
A100: Identify venue as per requirement (if not done at proposal stage) | B100: C+7 | C100: =Legend!$C$9+7 -> 46108 | D100: Working on RFP
A101: Finalize venue and block | B101: C+15 | C101: =Legend!$C$9+15 -> 46116 | D101: Planning
A102: Pay advance, if needed | B102: P-30 | C102: =Legend!$C$11-30 -> 46100 | D102: Delivery | E102: could vary
A103: Re-confirm exact AV etc. requirement from client | B103: P-15 | C103: =Legend!$C$11-15 -> 46115 | D103: Delivery
A104: Share AV etc. requirement details to vendor | B104: P-7 | C104: =Legend!$C$11-7 -> 46123 | D104: Delivery
A105: Re-confirm all arrangements | B105: P-1 | C105: =Legend!$C$11-1 -> 46129 | D105: Delivery
A108: Transport
A109: Name | B109: Timeframe (Date) | C109: Timeframe (Date) | D109: Milestone | E109: Notes | F109: Process # | G109: Timeline - Start | H109: Timeline - End
A110: Confirm requirement for each destination / specific visits or requirements (e.g. seatbelts, wheelchair acess etc.) | B110: R+1 | C110: =Legend!$C$5+1 -> 46083 | D110: Working on RFP
A111: Confirm requirement for each destination / specific visits or requirements (e.g. seatbelts, wheelchair acess etc.) | B111: C | C111: =Legend!$C$9 -> 46101 | D111: Planning
A112: Contact DMC / local transport vendor with the requirement | B112: R+1 | C112: =Legend!$C$5+1 -> 46083 | D112: Working on RFP
A113: Contact DMC / local transport vendor with the requirement | B113: C+1 | C113: =Legend!$C$9+1 -> 46102 | D113: Planning
A114: Block chosen vehicles | B114: C+15 | C114: =Legend!$C$9+15 -> 46116 | D114: Planning
A115: Send tentative itinerary to check about routes, timings or any specific requirements/issues | B115: P-30 | C115: =Legend!$C$11-30 -> 46100 | D115: Planning
A116: Send reminder about flight details to cient | B116: P-30 | C116: =Legend!$C$11-30 -> 46100 | D116: Delivery
A117: Receive arrival and departure details from client | B117: P-15 | C117: =Legend!$C$11-15 -> 46115 | D117: Delivery
...

Sheet Faculty Led Programs
A1: Operations Process (Proposal to Delivery)
A3: Action Items while sending proposals
A4: Name | B4: Timeframe (Date) | C4: Timeframe (Date) | D4: Milestone | E4: Notes | F4: Process # | G4: Timeline - Start | H4: Timeline - End
A5: Ensure sales hand-off template is filled; clarify doubts, if any before working on the proposal | B5: R | C5: =Legend!$C$5 -> 46082 | D5: Working on RFP
A6: Use itinerary elements template to detail out the requirements | B6: R+1 | C6: =Legend!$C$5+1 -> 46083 | D6: Working on RFP
A7: Get quotes from DMCs/hotels for program dates | B7: R+1 | C7: =Legend!$C$5+1 -> 46083 | D7: Working on RFP | E7: Using vendor templates
A8: Finalize hotel options for the proposal | B8: R+7 | C8: =Legend!$C$5+7 -> 46089 | D8: Working on RFP | E8: Using hotel sheet template
A9: Complete and review the costing sheet and proposal | B9: R+7 | C9: =Legend!$C$5+7 -> 46089 | D9: Working on RFP | E9: Use formats
A10: Block all proposed hotels and guides | B10: S | C10: =Legend!$C$7 -> 46096 | D10: Working on RFP | E10: ensure payments & cancellation are on agreeable terms
A11: Followup with client/sales on the proposal status to release or keep the blocks | B11: S+15 | C11: =Legend!$C$7+15 -> 46111 | D11: Working on RFP | E11: Proposal confirmation timeline could vary
A13: Action Items after proposal is won
A14: Name | B14: Timeframe (Date) | C14: Timeframe (Date) | D14: Milestone | E14: Notes | F14: Process # | G14: Timeline - Start | H14: Timeline - End
A15: Sign contracts with hotels and DMCs | B15: P-90 | C15: =Legend!$C$11-90 -> 46040 | D15: Planning | E15: timeframe could vary
A16: Followup with client/sales on program confirmation date | B16: P-90 | C16: =Legend!$C$11-90 -> 46040 | D16: Planning | E16: timeframe could vary
A18: Action Items after program confirmation
A19: Name | B19: Timeframe (Date) | C19: Timeframe (Date) | D19: Milestone | E19: Notes | F19: Process # | G19: Timeline - Start | H19: Timeline - End
A20: Send deposit invoice to university | B20: P-90 | C20: =Legend!$C$11-90 -> 46040 | D20: Planning | E20: Check proposal terms and conditions
A21: Create mastersheet | B21: C+1 | C21: =Legend!$C$9+1 -> 46102 | D21: Planning | E21: Use template and fill information on an on-going basis
A22: Set up Monday.com/google sheet for collaboration with all university stakeholders | B22: C+3 | C22: =Legend!$C$9+3 -> 46104 | D22: Planning | E22: ENHANCED: Real-time tracking
A23: Share participant data template to collect information (including scanned passport copies) | B23: C+7 | C23: =Legend!$C$9+7 -> 46108 | D23: Planning | E23: Use participant data template #to client
A24: Prepare for in-person/online program orientation and safety briefing | B24: P-30 | C24: =Legend!$C$11-30 -> 46100 | D24: Planning | E24: Refer to India orientation PPT
A25: Send balance invoice to university | B25: P-30 | C25: =Legend!$C$11-30 -> 46100 | D25: Planning
A26: Get confirmation on final service requirements from university | D26: Planning | E26: Confirm final group size, hotel blocks, transport, guides, meals, academic content and cultural immersions
A27: Send final program services agreement | C27: =Legend!$C$11-30 -> 46100 | D27: Planning
A28: Create and share pre-departure guide | B28: P-30 | C28: =Legend!$C$11-30 -> 46100 | D28: Planning | E28: Refer to standard pre dep template
A29: Create checklist for delivery | B29: P-15 | C29: =Legend!$C$11-15 -> 46115 | D29: Delivery | E29: Refer to mastersheet for template
A30: Plan and prepare first aid kits and other relevant material specific to programs | B30: P-7 | C30: =Legend!$C$11-7 -> 46123 | D30: Delivery
A31: Print checklists and relevant documents | B31: P-15 | C31: =Legend!$C$11-1 -> 46129 | D31: Delivery
A32: Send post program invoice to the university | B32: P+7 | C32: =Legend!$C$12 -> 46234 | D32: Delivery | E32: Enter Program end date + 7 days
A33: Send thank you notes to partner organizations / companies | B33: P+7 | C33: =Legend!$C$12 -> 46234 | D33: Delivery | E33: Send thank you notes on the same day of the visit (could vary based on the work load)
A36: Pre-departure planning
A37: Name | B37: Timeframe (Date) | C37: Timeframe (Date) | D37: Milestone | E37: Notes | F37: Process # | G37: Timeline - Start | H37: Timeline - End
A38: Mandatory vendor service specification documentation | B38: C+45 | C38: =Legend!$C$5+45 -> 46127 | D38: Working on RFP | E38: NEW: All limitations documented
A39: Complete program orientation for guides and local partners | B39: C+45 | C39: =Legend!$C$5+45 -> 46127 | D39: Working on RFP | E39: Brief them about Authentica standards
A42: Triple Verification Protocol
A43: Name | B43: Timeframe (Date) | C43: Timeframe (Date) | D43: Milestone | E43: Notes | F43: Process # | G43: Timeline - Start | H43: Timeline - End
A44: Verify pre-program delivery checklist | B44: P-7 | C44: =Legend!$C$11-7 -> 46123 | D44: Planning | E44: Refer template
A46: Hotels
A47: Name | B47: Timeframe (Date) | C47: Timeframe (Date) | D47: Milestone | E47: Notes | F47: Process # | G47: Timeline - Start | H47: Timeline - End
A48: Block and sign contracts with chosen hotels and procure invoices with payment details | B48: C+1 | C48: =Legend!$C$9+1 -> 46102 | D48: Planning | E48: As per updated numbers received from the university
A49: Release block for other hotels across locations | B49: C+1 | C49: =Legend!$C$9+1 -> 46102 | D49: Planning
A50: Send advance to chosen hotels: CCA / bank transfer / outward remittance | B50: C+30 | C50: =Legend!$C$9+30 -> 46131 | D50: Delivery | E50: could vary
A51: Collect rooming list from client and send it to hotels | B51: P-15 | C51: =Legend!$C$11-15 -> 46115 | D51: Delivery
A53: Flight/Train bookings
A54: Name | B54: Timeframe (Date) | C54: Timeframe (Date) | D54: Milestone | E54: Notes | F54: Process # | G54: Timeline - Start | H54: Timeline - End
A55: Confirm preferred flight/train option with client | B55: C+1 | C55: =Legend!$C$9+1 -> 46102 | D55: Delivery | E55: could vary
A56: Collect participant information / passport scans | B56: C+7 | C56: =Legend!$C$9+7 -> 46108 | D56: Delivery | E56: could vary
A57: Book tickets (either with vendor or directly online) and share tickets with university | B57: C+15 | C57: =Legend!$C$9+15 -> 46116 | D57: Delivery | E57: could vary
A59: Guides
A60: Name | B60: Timeframe (Date) | C60: Timeframe (Date) | D60: Milestone | E60: Notes | F60: Process # | G60: Timeline - Start | H60: Timeline - End
A61: Book dates of preferred guides (Directly or with DMC) | B61: C+1 | C61: =Legend!$C$9+1 -> 46102 | D61: Planning
A62: Send draft itinerary to guides/DMC along with the academic objective briefing | B62: P-30 | C62: =Legend!$C$11-30 -> 46100 | D62: Planning
A63: Send final itinerary / checklist and PAX info to guides | B63: P-7 | C63: =Legend!$C$11-7 -> 46123 | D63: Delivery | E63: could vary
A64: Send advance for entrance fees etc. | B64: P-7 | C64: =Legend!$C$11-7 -> 46123 | D64: Delivery
A66: Meeting Rooms
A67: Name | B67: Timeframe (Date) | C67: Timeframe (Date) | D67: Milestone | E67: Notes | F67: Process # | G67: Timeline - Start | H67: Timeline - End
A68: Confirm exact requirement from client (preferred venue location, purpose of meeting, group size, AV requirement, F&B etc.) | B68: C+1 | C68: =Legend!$C$9+1 -> 46102 | D68: Working on RFP
A69: Identify, block and finalize venue | B69: C+15 | C69: =Legend!$C$9+15 -> 46116 | D69: Planning
A70: Pay advance, if needed | B70: P-30 | C70: =Legend!$C$11-30 -> 46100 | D70: Delivery | E70: could vary
A71: Re-confirm exact requirements from university and share it with vendors | B71: P-15 | C71: =Legend!$C$11-15 -> 46115 | D71: Delivery
A73: Transport
A74: Name | B74: Timeframe (Date) | C74: Timeframe (Date) | D74: Milestone | E74: Notes | F74: Process # | G74: Timeline - Start | H74: Timeline - End
A75: Confirm requirement for each destination / specific visits or requirements (e.g. seatbelts, wheelchair acess etc.) and share with vendors/DMC | B75: C | C75: =Legend!$C$9 -> 46101 | D75: Planning
A76: Send transport/DMC itinerary to check about routes, timings or any specific requirements/issues | B76: P-30 | C76: =Legend!$C$11-30 -> 46100 | D76: Planning
A77: Share arrival and departure schedule to university and share it with vendors/DMC | B77: P-15 | C77: =Legend!$C$11-15 -> 46115 | D77: Delivery | E77: As per the mastersheet template
A78: Send final itinerary and placard | B78: P-7 | C78: =Legend!$C$11-7 -> 46123 | D78: Delivery | E78: Asian DMCs require this earlier
A80: Meals
A81: Name | B81: Timeframe (Date) | C81: Timeframe (Date) | D81: Milestone | E81: Notes | F81: Process # | G81: Timeline - Start | H81: Timeline - End
A82: Confirm meal requirements to be included | B82: C | C82: =Legend!$C$9 -> 46101 | D82: Planning
A83: Research appropriate options in each destination (if not done already) | B83: C+7 | C83: =Legend!$C$9+7 -> 46108 | D83: Planning | E83: sometimes we have specific seating requirement
A84: Contact shortlisted venues to get availability, rates and menu details | B84: C+15 | C84: =Legend!$C$9+15 -> 46116 | D84: Planning
A85: Finalilze and block chosen venues | B85: C+30 | C85: =Legend!$C$9+30 -> 46131 | D85: Delivery | E85: sometimes client approval is needed
A86: Pay advance, if needed | B86: P-30 | C86: =Legend!$C$11-30 -> 46100 | D86: Delivery
A87: Send dietary restrictions | B87: P-15 | C87: =Legend!$C$11-15 -> 46115 | D87: Delivery
A88: Finalize menu with dietary restrictions | B88: P-7 | C88: =Legend!$C$11-7 -> 46123 | D88: Delivery | E88: sometimes client approval is needed
A89: Reconfirm seating and menu | B89: P-1 | C89: =Legend!$C$11-1 -> 46129 | D89: Delivery
A90: START FROM HERE
A92: Immersions
A93: Name | B93: Timeframe (Date) | C93: Timeframe (Date) | D93: Milestone | E93: Notes | F93: Process # | G93: Timeline - Start | H93: Timeline - End
A94: Finalilze and block chosen options with any specific instruction (e.g. specific guides, atomic bomb survivor etc.) | B94: C+15 | C94: =Legend!$C$9+15 -> 46116 | D94: Planning | E94: sometimes client approval is needed
A95: Pay advance, if needed | B95: P-30 | C95: =Legend!$C$11-30 -> 46100 | D95: Planning
A97: Org Visits
A98: Name | B98: Timeframe (Date) | C98: Timeframe (Date) | D98: Milestone | E98: Notes | F98: Process # | G98: Timeline - Start | H98: Timeline - End
A99: Brief PDs/Content partners regarding program theme and requirements | B99: C+15 | C99: =Legend!$C$9+15 -> 46116 | D99: Planning
A100: Collect relevant info to be shared (e.g. bio book) from client | B100: P-30 | C100: =Legend!$C$11-30 -> 46100 | D100: Delivery
A101: Finalize visits in discussion with the client and PDs | B101: P-30 | C101: =Legend!$C$11-30 -> 46100 | D101: Delivery
A102: Get logistical contacts from PDs at for each visit | B102: P-30 | C102: =Legend!$C$11-30 -> 46100 | D102: Delivery
A103: Co-ordinate with organizations about the visit (timings, address, meals, security protocols like passports, roster sheet, license plate) | B103: P-15 | C103: =Legend!$C$11-15 -> 46115 | D103: Delivery
A104: Plan and procure gifts for organization visits | B104: P-30 | C104: =Legend!$C$11-30 -> 46100 | D104: Delivery
A107: Post Program Action items
A108: Name | B108: Timeframe (Date) | C108: Timeframe (Date) | D108: Milestone | E108: Notes | F108: Process # | G108: Timeline - Start | H108: Timeline - End
A109: Settle balance payments of all vendors
A110: Submit expense report to HQ
A111: Upload media to zoho drive
A112: Immediate debrief with all stakeholders within 48 hours | B112: P+15 | C112: =Legend!$C$12+15 -> 46249 | D112: Delivery | E112: NEW: Rapid issue identification
A113: Service failure compensation processing | B113: P+15 | C113: =Legend!$C$12+15 -> 46249 | D113: Delivery | E113: NEW: Proactive client relations
A114: Local partner performance evaluation | B114: P+15 | C114: =Legend!$C$12+15 -> 46249 | D114: Delivery | E114: NEW: Continuous improvement
A115: Process improvement documentation | B115: P+15 | C115: =Legend!$C$12+15 -> 46249 | D115: Delivery | E115: Use learnings template in Mastersheet
A116: Client satisfaction follow-up call | B116: P+15 | C116: =Legend!$C$12+15 -> 46249 | D116: Delivery | E116: NEW: Relationship management
A121: Document Version History
...

Sheet Internships
A1: Operations Process (Proposal to Delivery)
A3: Action Items while sending proposals
A4: Name | B4: Timeframe (Date) | C4: Timeframe (Date) | D4: Milestone | E4: Notes | F4: Process # | G4: Timeline - Start | H4: Timeline - End
A5: Ensure sales hand-off template is filled; clarify doubts, if any before working on the proposal | B5: R | C5: =Legend!$C$5 -> 46082 | D5: Working on RFP
A6: Use itinerary elements template to detail out the requirements | B6: R+1 | C6: =Legend!$C$5+1 -> 46083 | D6: Working on RFP
A7: Get quotes from DMCs/hotels for program dates | B7: R+1 | C7: =Legend!$C$5+1 -> 46083 | D7: Working on RFP | E7: Using vendor templates
A8: Finalize hotel options for the proposal | B8: R+7 | C8: =Legend!$C$5+7 -> 46089 | D8: Working on RFP | E8: Using hotel sheet template
A9: Complete and review the costing sheet and proposal | B9: R+7 | C9: =Legend!$C$5+7 -> 46089 | D9: Working on RFP | E9: Use formats
A10: Block all proposed hotels and guides | B10: S | C10: =Legend!$C$7 -> 46096 | D10: Working on RFP | E10: ensure payments & cancellation are on agreeable terms
A11: Followup with client/sales on the proposal status to release or keep the blocks | B11: S+15 | C11: =Legend!$C$7+15 -> 46111 | D11: Working on RFP | E11: Proposal confirmation timeline could vary
A13: Action Items after proposal is won
A14: Name | B14: Timeframe (Date) | C14: Timeframe (Date) | D14: Milestone | E14: Notes | F14: Process # | G14: Timeline - Start | H14: Timeline - End
A15: Sign contracts with hotels and DMCs | B15: P-90 | C15: =Legend!$C$11-90 -> 46040 | D15: Planning | E15: timeframe could vary
A16: Followup with client/sales on program confirmation date | B16: P-90 | C16: =Legend!$C$11-90 -> 46040 | D16: Planning | E16: timeframe could vary
A18: Action Items after program confirmation
A19: Name | B19: Timeframe (Date) | C19: Timeframe (Date) | D19: Milestone | E19: Notes | F19: Process # | G19: Timeline - Start | H19: Timeline - End
A20: Send deposit invoice to university | B20: P-90 | C20: =Legend!$C$11-90 -> 46040 | D20: Planning | E20: Check proposal terms and conditions
A21: Create mastersheet | B21: C+1 | C21: =Legend!$C$9+1 -> 46102 | D21: Planning | E21: Use template and fill information on an on-going basis
A22: Set up Monday.com/google sheet for collaboration with all university stakeholders | B22: C+3 | C22: =Legend!$C$9+3 -> 46104 | D22: Planning | E22: ENHANCED: Real-time tracking
A23: Share participant data template to collect information (including scanned passport copies) | B23: C+7 | C23: =Legend!$C$9+7 -> 46108 | D23: Planning | E23: Use participant data template #to client
A24: Prepare for in-person/online program orientation and safety briefing | B24: P-30 | C24: =Legend!$C$11-30 -> 46100 | D24: Planning | E24: Refer to India orientation PPT
A25: Send balance invoice to university | B25: P-30 | C25: =Legend!$C$11-30 -> 46100 | D25: Planning
A26: Get confirmation on final service requirements from university | D26: Planning | E26: Confirm final group size, hotel blocks, transport, guides, meals, academic content and cultural immersions
A27: Send final program services agreement | C27: =Legend!$C$11-30 -> 46100 | D27: Planning
A28: Create and share pre-departure guide | B28: P-30 | C28: =Legend!$C$11-30 -> 46100 | D28: Planning | E28: Refer to standard pre dep template
A29: Create checklist for delivery | B29: P-15 | C29: =Legend!$C$11-15 -> 46115 | D29: Delivery | E29: Refer to mastersheet for template
A30: Plan and prepare first aid kits and other relevant material specific to programs | B30: P-7 | C30: =Legend!$C$11-7 -> 46123 | D30: Delivery
A31: Print checklists and relevant documents | B31: P-15 | C31: =Legend!$C$11-1 -> 46129 | D31: Delivery
A32: Send post program invoice to the university | B32: P+7 | C32: =Legend!$C$12 -> 46234 | D32: Delivery | E32: Enter Program end date + 7 days
A33: Send thank you notes to partner organizations / companies | B33: P+7 | C33: =Legend!$C$12 -> 46234 | D33: Delivery | E33: Send thank you notes on the same day of the visit (could vary based on the work load)
A36: Pre-departure planning
A37: Name | B37: Timeframe (Date) | C37: Timeframe (Date) | D37: Milestone | E37: Notes | F37: Process # | G37: Timeline - Start | H37: Timeline - End
A38: Mandatory vendor service specification documentation | B38: C+45 | C38: =Legend!$C$5+45 -> 46127 | D38: Working on RFP | E38: NEW: All limitations documented
A39: Complete program orientation for guides and local partners | B39: C+45 | C39: =Legend!$C$5+45 -> 46127 | D39: Working on RFP | E39: Brief them about Authentica standards
A42: Triple Verification Protocol
A43: Name | B43: Timeframe (Date) | C43: Timeframe (Date) | D43: Milestone | E43: Notes | F43: Process # | G43: Timeline - Start | H43: Timeline - End
A44: Verify pre-program delivery checklist | B44: P-7 | C44: =Legend!$C$11-7 -> 46123 | D44: Planning | E44: Refer template
A46: Hotels
A47: Name | B47: Timeframe (Date) | C47: Timeframe (Date) | D47: Milestone | E47: Notes | F47: Process # | G47: Timeline - Start | H47: Timeline - End
A48: Block and sign contracts with chosen hotels and procure invoices with payment details | B48: C+1 | C48: =Legend!$C$9+1 -> 46102 | D48: Planning | E48: As per updated numbers received from the university
A49: Release block for other hotels across locations | B49: C+1 | C49: =Legend!$C$9+1 -> 46102 | D49: Planning
A50: Send advance to chosen hotels: CCA / bank transfer / outward remittance | B50: C+30 | C50: =Legend!$C$9+30 -> 46131 | D50: Delivery | E50: could vary
A51: Collect rooming list from client and send it to hotels | B51: P-15 | C51: =Legend!$C$11-15 -> 46115 | D51: Delivery
A53: Flight/Train bookings
A54: Name | B54: Timeframe (Date) | C54: Timeframe (Date) | D54: Milestone | E54: Notes | F54: Process # | G54: Timeline - Start | H54: Timeline - End
A55: Confirm preferred flight/train option with client | B55: C+1 | C55: =Legend!$C$9+1 -> 46102 | D55: Delivery | E55: could vary
A56: Collect participant information / passport scans | B56: C+7 | C56: =Legend!$C$9+7 -> 46108 | D56: Delivery | E56: could vary
A57: Book tickets (either with vendor or directly online) and share tickets with university | B57: C+15 | C57: =Legend!$C$9+15 -> 46116 | D57: Delivery | E57: could vary
A59: Guides
A60: Name | B60: Timeframe (Date) | C60: Timeframe (Date) | D60: Milestone | E60: Notes | F60: Process # | G60: Timeline - Start | H60: Timeline - End
A61: Book dates of preferred guides (Directly or with DMC) | B61: C+1 | C61: =Legend!$C$9+1 -> 46102 | D61: Planning
A62: Send draft itinerary to guides/DMC along with the academic objective briefing | B62: P-30 | C62: =Legend!$C$11-30 -> 46100 | D62: Planning
A63: Send final itinerary / checklist and PAX info to guides | B63: P-7 | C63: =Legend!$C$11-7 -> 46123 | D63: Delivery | E63: could vary
A64: Send advance for entrance fees etc. | B64: P-7 | C64: =Legend!$C$11-7 -> 46123 | D64: Delivery
A66: Meeting Rooms
A67: Name | B67: Timeframe (Date) | C67: Timeframe (Date) | D67: Milestone | E67: Notes | F67: Process # | G67: Timeline - Start | H67: Timeline - End
A68: Confirm exact requirement from client (preferred venue location, purpose of meeting, group size, AV requirement, F&B etc.) | B68: C+1 | C68: =Legend!$C$9+1 -> 46102 | D68: Working on RFP
A69: Identify, block and finalize venue | B69: C+15 | C69: =Legend!$C$9+15 -> 46116 | D69: Planning
A70: Pay advance, if needed | B70: P-30 | C70: =Legend!$C$11-30 -> 46100 | D70: Delivery | E70: could vary
A71: Re-confirm exact requirements from university and share it with vendors | B71: P-15 | C71: =Legend!$C$11-15 -> 46115 | D71: Delivery
A73: Transport
A74: Name | B74: Timeframe (Date) | C74: Timeframe (Date) | D74: Milestone | E74: Notes | F74: Process # | G74: Timeline - Start | H74: Timeline - End
A75: Confirm requirement for each destination / specific visits or requirements (e.g. seatbelts, wheelchair acess etc.) and share with vendors/DMC | B75: C | C75: =Legend!$C$9 -> 46101 | D75: Planning
A76: Send transport/DMC itinerary to check about routes, timings or any specific requirements/issues | B76: P-30 | C76: =Legend!$C$11-30 -> 46100 | D76: Planning
A77: Share arrival and departure schedule to university and share it with vendors/DMC | B77: P-15 | C77: =Legend!$C$11-15 -> 46115 | D77: Delivery | E77: As per the mastersheet template
A78: Send final itinerary and placard | B78: P-7 | C78: =Legend!$C$11-7 -> 46123 | D78: Delivery | E78: Asian DMCs require this earlier
A80: Meals
A81: Name | B81: Timeframe (Date) | C81: Timeframe (Date) | D81: Milestone | E81: Notes | F81: Process # | G81: Timeline - Start | H81: Timeline - End
A82: Confirm meal requirements to be included | B82: C | C82: =Legend!$C$9 -> 46101 | D82: Planning
A83: Research appropriate options in each destination (if not done already) | B83: C+7 | C83: =Legend!$C$9+7 -> 46108 | D83: Planning | E83: sometimes we have specific seating requirement
A84: Contact shortlisted venues to get availability, rates and menu details | B84: C+15 | C84: =Legend!$C$9+15 -> 46116 | D84: Planning
A85: Finalilze and block chosen venues | B85: C+30 | C85: =Legend!$C$9+30 -> 46131 | D85: Delivery | E85: sometimes client approval is needed
A86: Pay advance, if needed | B86: P-30 | C86: =Legend!$C$11-30 -> 46100 | D86: Delivery
A87: Send dietary restrictions | B87: P-15 | C87: =Legend!$C$11-15 -> 46115 | D87: Delivery
A88: Finalize menu with dietary restrictions | B88: P-7 | C88: =Legend!$C$11-7 -> 46123 | D88: Delivery | E88: sometimes client approval is needed
A89: Reconfirm seating and menu | B89: P-1 | C89: =Legend!$C$11-1 -> 46129 | D89: Delivery
A90: START FROM HERE
A92: Immersions
A93: Name | B93: Timeframe (Date) | C93: Timeframe (Date) | D93: Milestone | E93: Notes | F93: Process # | G93: Timeline - Start | H93: Timeline - End
A94: Finalilze and block chosen options with any specific instruction (e.g. specific guides, atomic bomb survivor etc.) | B94: C+15 | C94: =Legend!$C$9+15 -> 46116 | D94: Planning | E94: sometimes client approval is needed
A95: Pay advance, if needed | B95: P-30 | C95: =Legend!$C$11-30 -> 46100 | D95: Planning
A97: Org Visits
A98: Name | B98: Timeframe (Date) | C98: Timeframe (Date) | D98: Milestone | E98: Notes | F98: Process # | G98: Timeline - Start | H98: Timeline - End
A99: Brief PDs/Content partners regarding program theme and requirements | B99: C+15 | C99: =Legend!$C$9+15 -> 46116 | D99: Planning
A100: Collect relevant info to be shared (e.g. bio book) from client | B100: P-30 | C100: =Legend!$C$11-30 -> 46100 | D100: Delivery
A101: Finalize visits in discussion with the client and PDs | B101: P-30 | C101: =Legend!$C$11-30 -> 46100 | D101: Delivery
A102: Get logistical contacts from PDs at for each visit | B102: P-30 | C102: =Legend!$C$11-30 -> 46100 | D102: Delivery
A103: Co-ordinate with organizations about the visit (timings, address, meals, security protocols like passports, roster sheet, license plate) | B103: P-15 | C103: =Legend!$C$11-15 -> 46115 | D103: Delivery
A104: Plan and procure gifts for organization visits | B104: P-30 | C104: =Legend!$C$11-30 -> 46100 | D104: Delivery
A106: Projects for Internships
A107: Name | B107: Timeframe (Date) | C107: Timeframe (Date) | D107: Milestone | E107: Notes | F107: Process # | G107: Timeline - Start | H107: Timeline - End
A108: Confirm criteria for projects | B108: C | C108: =Legend!$C$9 -> 46101 | D108: Workng on RFP
A109: Identify relevant orgs and contact them with a template email with requirements | B109: C+15 | C109: =Legend!$C$9+15 -> 46116 | D109: Workng on RFP
A110: Shortlist relevant / interested orgs and share their details to the client | B110: C+30 | C110: =Legend!$C$9+30 -> 46131 | D110: Workng on RFP | E110: this might take longer
A111: Discuss project scope and help orgs draft project description | B111: P-60 | C111: =Legend!$C$11-60 -> 46070 | D111: Workng on RFP | E111: time-frame could vary
A112: Finalize project description and share with client | B112: P-30 | C112: =Legend!$C$11-30 -> 46100 | D112: Planning | E112: time-frame could vary
A113: Ensure org is ready to host group | B113: P-15 | C113: =Legend!$C$11-15 -> 46115 | D113: Planning
A114: Send/collect relevant info and share with group (address, timings, specific procedure for first day etc.) | B114: P-7 | C114: =Legend!$C$11-7 -> 46123 | D114: Delivery
A115: Reconfirm all arrangements | B115: P-1 | C115: =Legend!$C$11-1 -> 46129 | D115: Delivery
A116: Accompany group to org location and ensure they are well settled | B116: P | C116: =Legend!$C$11 -> 46130 | D116: Delivery
...

Sheet QC Checklist
A3: Action Items while sending proposals
A4: Name | B4: Timeframe (Date) | C4: Timeframe (Date) | D4: Milestone | E4: Notes | F4: Process # | G4: Timeline - Start | H4: Timeline - End
A5: Document all vendor service limitations and requirements | B5: R+7 | C5: =Legend!$C$5+7 -> 46089 | D5: Working on RFP | E5: NEW: Capture luggage transfer limits, group size restrictions, etc.
A6: Verify accommodation standards meet university requirements (private bathrooms, accessibility) | B6: R+7 | C6: =Legend!$C$5+7 -> 46089 | D6: Working on RFP | E6: NEW: Based on Cats Hostel Madrid issue
A7: Include detailed transportation requirements template (airport transfers, public transit specifications) | B7: S-1 | C7: =Legend!$C$7-1 -> 46095 | D7: Working on RFP | E7: NEW: Based on Barcelona transit confusion
A8: Implement triple verification system for all bookings | B8: C+3 | C8: =Legend!$C$9+3 -> 46104 | D8: Planning | E8: ENHANCED: Real-time tracking
A9: Establish clear protocols for mid-program change requests | B9: P-30 | C9: =Legend!$C$11-30 -> 46100 | D9: Planning | E9: NEW: Based on OSU budget change requests Add this point to services agreement
A10: Include comprehensive service limitations in student materials | B10: P-30 | C10: =Legend!$C$11-30 -> 46100 | D10: Planning | E10: ENHANCED: Luggage specs, transit rules Add this point to services agreement
A11: Accessibility assessment for all activities and routes | B11: C+40 | C11: =Legend!$C$5+40 -> 46122 | D11: Working on RFP | E11: NEW: San Sebastian route equity issue
A12: Weather contingency planning for all group activities | B12: C+35 | C12: =Legend!$C$5+35 -> 46117 | D12: Working on RFP | E12: NEW: San Sebastian dinner issue
A13: Restaurant proximity verification (max 10min walk from accommodations) | B13: C+35 | C13: =Legend!$C$5+35 -> 46117 | D13: Working on RFP | E13: NEW: Spain group dinner locations
A15: Continue updating mastersheet on regular basis | B15: P-7 | C15: =Legend!$C$11-7 -> 46123 | D15: Delivery
A16: Note any additional expenses beyond what we have invoiced for | B16: P | C16: =Legend!$C$11-7 -> 46123 | D16: Delivery | E16: Update the "post program invoice" tab in the mastersheet
A19: Send payment links to individuals for single supp/extra nights/activities (e.g. baseball match) etc. | B19: P | C19: =Legend!$C$11-7 -> 46123 | D19: Delivery | E19: time-frame could vary
A22: Triple Verification Protocol
A23: Name | B23: Timeframe (Date) | C23: Timeframe (Date) | D23: Milestone | E23: Notes | F23: Process # | G23: Timeline - Start | H23: Timeline - End
A24: First verification: All bookings confirmed with vendors | B24: P-15 | C24: =Legend!$C$11-15 -> 46115 | D24: Planning | E24: NEW: Screenshot confirmations required
A25: Second verification: Room counts, amenity specifications | B25: P-7 | C25: =Legend!$C$11-7 -> 46123 | D25: Planning | E25: NEW: Private bathroom verification
A26: Third verification: Final headcount updates to all vendors | B26: P-2 | C26: =Legend!$C$11-2 -> 46128 | D26: Delivery | E26: NEW: Prevent overbooking issues
A27: Pre-program vendor briefing calls (hotels, transport, guides) | B27: P-2 | C27: =Legend!$C$11-2 -> 46128 | D27: Delivery | E27: NEW: 72-hour advance coordination
A28: Transit pass delivery confirmation (24hrs before first use) | B28: P-2 | C28: =Legend!$C$11-2 -> 46128 | D28: Delivery | E28: NEW: San Sebastian dinner issue prevention
A29: Driver briefing with printed itineraries in local language | B29: P-2 | C29: =Legend!$C$11-2 -> 46128 | D29: Delivery | E29: NEW: Spain bus coordination issue
A32: Hotels
A33: Ensure rooms are allocated as per requirement and sort out any issues with the rooms in discussion with the duty manager | B33: P-1 | C33: =Legend!$C$11-1 -> 46129 | D33: Delivery
A35: Guides
A36: Be in touch on a daily basis to ensure things are going as per plan / discuss necessary modifications | B36: P | C36: =Legend!$C$11 -> 46130 | D36: Delivery
A39: Meeting Rooms
A40: Re-confirm all arrangements | B40: P-1 | C40: =Legend!$C$11-1 -> 46129 | D40: Delivery
A42: Transport
A43: Get driver details and confirm he has correct placard and itinerary | B43: P-1 | C43: =Legend!$C$11-1 -> 46129 | D43: Delivery
A44: Ensure driver knows the route / addresses and ensure tips are paid at the end | B44: P | C44: =Legend!$C$11-30 -> 46100 | D44: Delivery | E44: to be done a day in advance
A45: Ensure tips are paid to each driver on the last day / EOD | B45: P | C45: =Legend!$C$11-30 -> 46100 | D45: Delivery
A47: Immersions
A48: Reconfirm all arrangements | B48: P-1 | C48: =Legend!$C$11-1 -> 46129 | D48: Delivery
A50: Org Visits
A51: Reconfirm visit | B51: P-15 | C51: =Legend!$C$11-1 -> 46129 | D51: Delivery
A52: Ensure group reaches 10 mins. before meeting time and driver is ready at the end of the meeting | B52: P | C52: =Legend!$C$11 -> 46130 | D52: Delivery
A53: Give gifts to our contacts | B53: P | C53: =Legend!$C$11 -> 46130 | D53: Delivery
A54: Send thank you notes to org contacts and collect feedback (if any) | B54: P | C54: =Legend!$C$11 -> 46130 | D54: Delivery | E54: within 24 hours of visit
A56: Daily Operations Protocol
A57: Program Delivery
A58: Name | B58: Timeframe (Date) | C58: Timeframe (Date) | D58: Milestone | E58: Notes | F58: Process # | G58: Timeline - Start | H58: Timeline - End
A59: Evening debrief meetings with APM and faculty | B59: Daily | C59: - | D59: Delivery | E59: NEW: Address emerging issues
A60: Vendor reconfirmation for next day activities | B60: Daily | C60: - | D60: Delivery | E60: NEW: Prevent last-minute surprises
A61: Weather and contingency plan review | B61: Daily | C61: - | D61: Delivery | E61: NEW: Proactive planning
A62: Group cohesion monitoring and accommodation equity checks | B62: Daily | C62: - | D62: Delivery | E62: NEW: Prevent split group issues
A65: Enhanced Safety & Communication
A66: Name | B66: Timeframe (Date) | C66: Timeframe (Date) | D66: Milestone | E66: Notes | F66: Process # | G66: Timeline - Start | H66: Timeline - End
A67: WhatsApp group management (separate faculty/student groups) | B67: Real-time | C67: - | D67: Delivery | E67: ENHANCED: Improved communication
A68: Daily safety protocol verification with drivers | B68: Daily | C68: - | D68: Delivery | E68: NEW: Spain bus safety incident prevention
A69: Emergency budget activation protocols | B69: As needed | C69: - | D69: Delivery | E69: NEW: Weather-related backup plans
